{
  "type": "Program",
  "body": [
    {
      "type": "ImportDeclaration",
      "specifiers": [
        {
          "type": "ImportSpecifier",
          "local": {
            "type": "Identifier",
            "name": "Observable",
            "range": [
              9,
              19
            ],
            "loc": {
              "start": {
                "line": 1,
                "column": 9
              },
              "end": {
                "line": 1,
                "column": 19
              }
            }
          },
          "imported": {
            "type": "Identifier",
            "name": "Observable",
            "range": [
              9,
              19
            ],
            "loc": {
              "start": {
                "line": 1,
                "column": 9
              },
              "end": {
                "line": 1,
                "column": 19
              }
            }
          },
          "range": [
            9,
            19
          ],
          "loc": {
            "start": {
              "line": 1,
              "column": 9
            },
            "end": {
              "line": 1,
              "column": 19
            }
          }
        }
      ],
      "source": {
        "type": "Literal",
        "value": "../../Observable",
        "raw": "'../../Observable'",
        "range": [
          27,
          45
        ],
        "loc": {
          "start": {
            "line": 1,
            "column": 27
          },
          "end": {
            "line": 1,
            "column": 45
          }
        }
      },
      "range": [
        0,
        46
      ],
      "loc": {
        "start": {
          "line": 1,
          "column": 0
        },
        "end": {
          "line": 1,
          "column": 46
        }
      }
    },
    {
      "type": "ImportDeclaration",
      "specifiers": [
        {
          "type": "ImportSpecifier",
          "local": {
            "type": "Identifier",
            "name": "_do",
            "range": [
              57,
              60
            ],
            "loc": {
              "start": {
                "line": 2,
                "column": 9
              },
              "end": {
                "line": 2,
                "column": 12
              }
            }
          },
          "imported": {
            "type": "Identifier",
            "name": "_do",
            "range": [
              57,
              60
            ],
            "loc": {
              "start": {
                "line": 2,
                "column": 9
              },
              "end": {
                "line": 2,
                "column": 12
              }
            }
          },
          "range": [
            57,
            60
          ],
          "loc": {
            "start": {
              "line": 2,
              "column": 9
            },
            "end": {
              "line": 2,
              "column": 12
            }
          }
        }
      ],
      "source": {
        "type": "Literal",
        "value": "../../operator/do",
        "raw": "'../../operator/do'",
        "range": [
          68,
          87
        ],
        "loc": {
          "start": {
            "line": 2,
            "column": 20
          },
          "end": {
            "line": 2,
            "column": 39
          }
        }
      },
      "range": [
        48,
        88
      ],
      "loc": {
        "start": {
          "line": 2,
          "column": 0
        },
        "end": {
          "line": 2,
          "column": 40
        }
      }
    },
    {
      "type": "ExpressionStatement",
      "expression": {
        "type": "AssignmentExpression",
        "operator": "=",
        "left": {
          "type": "MemberExpression",
          "computed": false,
          "object": {
            "type": "MemberExpression",
            "computed": false,
            "object": {
              "type": "Identifier",
              "name": "Observable",
              "range": [
                90,
                100
              ],
              "loc": {
                "start": {
                  "line": 3,
                  "column": 0
                },
                "end": {
                  "line": 3,
                  "column": 10
                }
              }
            },
            "property": {
              "type": "Identifier",
              "name": "prototype",
              "range": [
                101,
                110
              ],
              "loc": {
                "start": {
                  "line": 3,
                  "column": 11
                },
                "end": {
                  "line": 3,
                  "column": 20
                }
              }
            },
            "range": [
              90,
              110
            ],
            "loc": {
              "start": {
                "line": 3,
                "column": 0
              },
              "end": {
                "line": 3,
                "column": 20
              }
            }
          },
          "property": {
            "type": "Identifier",
            "name": "do",
            "range": [
              111,
              113
            ],
            "loc": {
              "start": {
                "line": 3,
                "column": 21
              },
              "end": {
                "line": 3,
                "column": 23
              }
            }
          },
          "range": [
            90,
            113
          ],
          "loc": {
            "start": {
              "line": 3,
              "column": 0
            },
            "end": {
              "line": 3,
              "column": 23
            }
          }
        },
        "right": {
          "type": "Identifier",
          "name": "_do",
          "range": [
            116,
            119
          ],
          "loc": {
            "start": {
              "line": 3,
              "column": 26
            },
            "end": {
              "line": 3,
              "column": 29
            }
          }
        },
        "range": [
          90,
          119
        ],
        "loc": {
          "start": {
            "line": 3,
            "column": 0
          },
          "end": {
            "line": 3,
            "column": 29
          }
        }
      },
      "range": [
        90,
        120
      ],
      "loc": {
        "start": {
          "line": 3,
          "column": 0
        },
        "end": {
          "line": 3,
          "column": 30
        }
      }
    },
    {
      "type": "ExpressionStatement",
      "expression": {
        "type": "AssignmentExpression",
        "operator": "=",
        "left": {
          "type": "MemberExpression",
          "computed": false,
          "object": {
            "type": "MemberExpression",
            "computed": false,
            "object": {
              "type": "Identifier",
              "name": "Observable",
              "range": [
                122,
                132
              ],
              "loc": {
                "start": {
                  "line": 4,
                  "column": 0
                },
                "end": {
                  "line": 4,
                  "column": 10
                }
              }
            },
            "property": {
              "type": "Identifier",
              "name": "prototype",
              "range": [
                133,
                142
              ],
              "loc": {
                "start": {
                  "line": 4,
                  "column": 11
                },
                "end": {
                  "line": 4,
                  "column": 20
                }
              }
            },
            "range": [
              122,
              142
            ],
            "loc": {
              "start": {
                "line": 4,
                "column": 0
              },
              "end": {
                "line": 4,
                "column": 20
              }
            }
          },
          "property": {
            "type": "Identifier",
            "name": "_do",
            "range": [
              143,
              146
            ],
            "loc": {
              "start": {
                "line": 4,
                "column": 21
              },
              "end": {
                "line": 4,
                "column": 24
              }
            }
          },
          "range": [
            122,
            146
          ],
          "loc": {
            "start": {
              "line": 4,
              "column": 0
            },
            "end": {
              "line": 4,
              "column": 24
            }
          }
        },
        "right": {
          "type": "Identifier",
          "name": "_do",
          "range": [
            149,
            152
          ],
          "loc": {
            "start": {
              "line": 4,
              "column": 27
            },
            "end": {
              "line": 4,
              "column": 30
            }
          }
        },
        "range": [
          122,
          152
        ],
        "loc": {
          "start": {
            "line": 4,
            "column": 0
          },
          "end": {
            "line": 4,
            "column": 30
          }
        }
      },
      "range": [
        122,
        153
      ],
      "loc": {
        "start": {
          "line": 4,
          "column": 0
        },
        "end": {
          "line": 4,
          "column": 31
        }
      },
      "trailingComments": [
        {
          "type": "Line",
          "value": "# sourceMappingURL=do.js.map",
          "range": [
            155,
            185
          ],
          "loc": {
            "start": {
              "line": 5,
              "column": 0
            },
            "end": {
              "line": 5,
              "column": 30
            }
          }
        }
      ]
    }
  ],
  "sourceType": "module",
  "range": [
    0,
    153
  ],
  "loc": {
    "start": {
      "line": 1,
      "column": 0
    },
    "end": {
      "line": 4,
      "column": 31
    }
  },
  "comments": [
    {
      "type": "Line",
      "value": "# sourceMappingURL=do.js.map",
      "range": [
        155,
        185
      ],
      "loc": {
        "start": {
          "line": 5,
          "column": 0
        },
        "end": {
          "line": 5,
          "column": 30
        }
      }
    }
  ]
}